deplodocker/__init__.py
deplodocker/cli.py
deplodocker/formatter.py
deplodocker/loader.py
deplodocker/stainer.py
deplodocker-0.2.1.dist-info/entry_points.txt
deplodocker-0.2.1.dist-info/LICENSE
deplodocker-0.2.1.dist-info/WHEEL
deplodocker-0.2.1.dist-info/METADATA
deplodocker-0.2.1.dist-info/RECORD
