Metadata-Version: 2.1
Name: deplodocker
Version: 0.2.1
Summary: Locker of dependency files for deploy in docker and etc.
Home-page: https://github.com/RCheese/deplodocker
License: MIT
Author: RCheese
Author-email: ruslan.v.samoylov@gmail.com
Requires-Python: >=3.8,<4.0
Classifier: Environment :: Console
Classifier: Intended Audience :: Developers
Classifier: Intended Audience :: Information Technology
Classifier: License :: OSI Approved :: MIT License
Classifier: Natural Language :: English
Classifier: Operating System :: MacOS
Classifier: Operating System :: Microsoft :: Windows
Classifier: Operating System :: POSIX
Classifier: Operating System :: POSIX :: Linux
Classifier: Programming Language :: Python
Classifier: Programming Language :: Python :: 3
Classifier: Programming Language :: Python :: 3 :: Only
Classifier: Programming Language :: Python :: 3.6
Classifier: Programming Language :: Python :: 3.7
Classifier: Programming Language :: Python :: 3.8
Classifier: Programming Language :: Python :: 3.9
Provides-Extra: speedups
Requires-Dist: PyYAML (>=5.3,<6.0)
Requires-Dist: click (>=7.1,<8.0)
Requires-Dist: orjson (>=3.4,<4.0); extra == "speedups"
Requires-Dist: toml (>=0.10,<0.11)
Project-URL: Repository, https://github.com/RCheese/deplodocker
